lando4/__init__.py
lando4/examples.py
lando4-0.1.2.dist-info/licenses/LICENSE
lando4-0.1.2.dist-info/METADATA
lando4-0.1.2.dist-info/WHEEL
lando4-0.1.2.dist-info/top_level.txt
lando4-0.1.2.dist-info/RECORD
