Metadata-Version: 2.4
Name: lando4
Version: 0.1.2
Summary: My personal example code package hehe
Author-email: Your Name <you@example.com>
License: MIT
Requires-Python: >=3.8
License-File: LICENSE
Dynamic: license-file
